[
  {
    "nombre": "",
    "fecha": "",
    "origen": "",
    "tipo-planta": "arbol",
    "frec-podar": "",
    "frec-regar": "",
    "frec-fertilizar": "",
    "tipo-clima": "calido",
    "notas-especiales": ""
  },
  {
    "nombre": "",
    "fecha": "",
    "origen": "",
    "tipo-planta": "arbol",
    "frec-podar": "",
    "frec-regar": "",
    "frec-fertilizar": "",
    "tipo-clima": "calido",
    "notas-especiales": ""
  },
  {
    "nombre": "",
    "fecha": "",
    "origen": "",
    "tipo-planta": "arbol",
    "frec-podar": "",
    "frec-regar": "",
    "frec-fertilizar": "",
    "tipo-clima": "calido",
    "notas-especiales": ""
  },
  {
    "nombre": "Adalberto",
    "fecha": "2023-12-07",
    "origen": "wa",
    "tipo-planta": "arbusto",
    "podar": "on",
    "frec-podar": "11",
    "frec-regar": "2",
    "frec-fertilizar": "3",
    "tipo-clima": "calido",
    "notas-especiales": "awdad"
  },
  {
    "nombre": "Adalberto",
    "fecha": "2023-12-07",
    "origen": "wa",
    "tipo-planta": "arbusto",
    "podar": "on",
    "frec-podar": "11",
    "frec-regar": "2",
    "frec-fertilizar": "4",
    "tipo-clima": "calido",
    "notas-especiales": "awdad"
  }
]